crawl4ai_mcp_service/__init__.py
crawl4ai_mcp_service/server.py
crawl4ai_mcp_service/server.v0.py
crawl4ai_mcp_service-0.1.0.dist-info/METADATA
crawl4ai_mcp_service-0.1.0.dist-info/WHEEL
crawl4ai_mcp_service-0.1.0.dist-info/entry_points.txt
crawl4ai_mcp_service-0.1.0.dist-info/RECORD
