Metadata-Version: 2.3
Name: crawl4ai-mcp-service
Version: 0.1.0
Summary: MCP server for Crawl4AI integration
Author-email: UncleCode <unclecode@kidocode.com>
Requires-Python: >=3.13
Requires-Dist: crawl4ai>=0.3.746
Requires-Dist: mcp>=1.0.0
Requires-Dist: python-dotenv>=1.0.1
